vishesh_helloworld/__init__.py
vishesh_helloworld/main.py
vishesh_helloworld-0.2.dist-info/METADATA
vishesh_helloworld-0.2.dist-info/WHEEL
vishesh_helloworld-0.2.dist-info/entry_points.txt
vishesh_helloworld-0.2.dist-info/top_level.txt
vishesh_helloworld-0.2.dist-info/RECORD
