Metadata-Version: 2.2
Name: vishesh-helloworld
Version: 0.2
Summary: A package to fetch and download programs from GitHub repository
Home-page: https://github.com/visheshj2005/leetcode
Author: Vishesh Jain
Author-email: visheshj2005@gmail.com
Classifier: Programming Language :: Python :: 3
Classifier: License :: OSI Approved :: MIT License
Classifier: Operating System :: OS Independent
Requires-Python: >=3.6
Dynamic: author
Dynamic: author-email
Dynamic: classifier
Dynamic: home-page
Dynamic: requires-python
Dynamic: summary
